ForwardStepwiseFeatureSelection/__init__.py
ForwardStepwiseFeatureSelection-1.3.9.dist-info/LICENSE.txt
ForwardStepwiseFeatureSelection-1.3.9.dist-info/METADATA
ForwardStepwiseFeatureSelection-1.3.9.dist-info/WHEEL
ForwardStepwiseFeatureSelection-1.3.9.dist-info/top_level.txt
ForwardStepwiseFeatureSelection-1.3.9.dist-info/RECORD
