Metadata-Version: 2.1
Name: ForwardStepwiseFeatureSelection
Version: 1.3.9
Summary: Performaning feature selection in forward stepwise selection maner.
Home-page: https://github.com/HindyDS/ForwardStepwiseFeatureSelection
Author: Hindy Yuen
Author-email: hindy888@hotmail.com
License: MIT
Keywords: forward stepwise features feature select selection machine learning data science computer science recursive feature elimination dimentionality reduction
Platform: UNKNOWN
Classifier: Development Status :: 5 - Production/Stable
Classifier: Intended Audience :: Developers
Classifier: Topic :: Software Development :: Build Tools
Classifier: License :: OSI Approved :: MIT License
Classifier: Programming Language :: Python :: 3.7
Classifier: Programming Language :: Python :: 3.8
Classifier: Programming Language :: Python :: 3.9
Requires-Python: >=3.6
License-File: LICENSE.txt
